{ "template" : "divorceminipetition",
  "values": {
    "caseDetails" : {
      "id": "1517833758870511",
      "jurisdiction": "DIVORCE",
      "state": "Issued",
      "case_type_id": "DIVORCE",
      "created_date": "2018-02-05T12:29:17.81",
      "last_modified": "2018-02-05T14:57:11.346",
      "security_classification": "PUBLIC",
      "case_data": {
        "D8caseReference": "LV17D80100",
        "D8PetitionerFirstName": "John",
        "D8PetitionerLastName": "Smith",
        "D8RespondentFirstName": "Jane",
        "D8RespondentLastName": "Jamed",
        "D8PetitionerContactDetailsConfidential": "share",
        "D8DivorceWho": "wife",
        "D8MarriagePetitionerName": "John Doe",
        "D8MarriageRespondentName": "Jenny Benny",
        "D8MarriageDate": "2001-02-02",
        "D8MarriagePlaceOfMarriage": "In a church",
        "D8ReasonForDivorce": "desertion",
        "D8DivorceCostsClaim": "NO",
        "D8FinancialOrder": "YES",
        "D8JurisdictionConnection": [
          "B",
          "C",
          "F"
        ],
        "D8LegalProceedings": "NO",
        "D8LegalProceedingsDetails": "Insert proper text for the legal proceeding details",
        "D8DerivedPetitionerCorrespondenceAddr": "82 Landor Road\nLondon\nSW9 9PE",
        "D8FinancialOrderFor": [
          "children"
        ],
        "D8DivorceClaimFrom": [
          "respondent"
        ],
        "D8ReasonForDivorceDesertionDetails": "He told me that he is going to his mother. ",    
        "D8ReasonForDivorceDesertionDate": "2015-02-01",
        "D8ReasonForDivorceDesertionAgreed": "YES",
        "D8ReasonForDivorceSeperationDate": "2011-01-01",
        "D8MentalSeparationDate": "2018-02-01",
        "D8PhysicalSeparationDate": "2018-03-01"
      }
    }
  }
}
